Workbook

Sheet Riepilogo
A1: Gen&Sys · Report social e ADV
A2: Periodo: 1 gennaio – 1 ottobre 2026 · Fonte: Windsor.ai (Facebook Organic, Instagram, Meta Ads) · Estratto il 16 ottobre 2026
A4: Facebook (pagina)
A5: Impression totali | B5: ='FB Mensile'!B15 -> 13387
A6: di cui sponsorizzate | B6: ='FB Mensile'!D15 -> 11525
A7: Quota sponsorizzata | B7: ='FB Mensile'!H15 -> 0.86090984
A8: Interazioni con i post | B8: ='FB Mensile'!E15 -> 383
A9: Visite alla pagina | B9: ='FB Mensile'!G15 -> 1021
A10: Nuovi follower nel periodo | B10: ='FB Mensile'!F15 -> 19
A11: Follower al 1 ottobre | B11: =INDEX('FB Giornaliero'!G5:G278,274) -> 19
A12: Post pubblicati (esclusi cambi foto profilo/copertina) | B12: =COUNTIFS('FB Post'!B5:B33,"<>Foto copertina",'FB Post'!B5:B33,"<>Foto profilo") -> 27
A14: Instagram (@genesys_srl)
A15: Visualizzazioni | B15: ='IG Mensile'!C15 -> 8323
A16: Interazioni totali | B16: ='IG Mensile'!D15 -> 168
A17: Follower (dato al 16 ottobre) | B17: 30
A18: Contenuti pubblicati | B18: =COUNTA('IG Contenuti'!A5:A31) -> 27
A20: Meta Ads (account Gen&Sys)
A21: Spesa totale (€) | B21: ='ADV Campagne'!C7 -> 347.69
A22: Impression a pagamento | B22: ='ADV Campagne'!D7 -> 120040
A23: Clic sul link | B23: ='ADV Campagne'!H7 -> 521
A24: Costo per clic sul link (€) | B24: ='ADV Campagne'!J7 -> 0.66735125
A25: CPM (€) | B25: ='ADV Campagne'!K7 -> 2.8964512
A26: Quota impression su Audience Network | B26: ='ADV Mese e piattaforma'!D29 -> 0.89163612
A28: Note
A29: • La campagna "[INTERAZIONI] Giugno 2026" risulta ancora attiva: ha speso anche dopo il 1 ottobre (dati fino al 16 ottobre, foglio ADV Campagne).
A30: • Quasi tutte le impression della campagna Interazioni sono su Audience Network (app e siti esterni a Meta), con pochissimi clic.
A31: • La campagna "[TRAFFICO] Reel IG" (11–30 settembre) ha un costo per clic sul link molto più basso.
A32: • Follower Instagram: Meta fornisce solo il totale del giorno di estrazione (valore in blu, inserito a mano).
A33: • Copertura Instagram mensile = somma della copertura giornaliera, non persone uniche.

Sheet ADV Campagne
A1: Meta Ads · campagne Gen&Sys (1 gen – 1 ott 2026)
A2: Account pubblicitario Gen&Sys (ID 1501696344256381), valori in EUR. Fonte: Windsor.ai, connettore Facebook Ads.
A4: Campagna | B4: Obiettivo | C4: Spesa (€) | D4: Impression | E4: Copertura | F4: Frequenza | G4: Clic (tutti) | H4: Clic sul link | I4: CTR link | J4: Costo per clic link (€) | K4: CPM (€) | L4: Riproduzioni video 3s | M4: Interazioni con il post | N4: Mi piace alla pagina
A5: [INTERAZIONI] Giugno 2026 | B5: OUTCOME_ENGAGEMENT | C5: 297.71 | D5: 108384 | E5: 19810 | F5: =IFERROR(D5/E5,0) -> 5.4711762 | G5: 172 | H5: 170 | I5: =IFERROR(H5/D5,0) -> 0.0015684972 | J5: =IFERROR(C5/H5,0) -> 1.7512353 | K5: =IFERROR(C5/D5*1000,0) -> 2.7468076 | L5: 106378 | M5: 106552 | N5: 0
A6: [TRAFFICO] Reel IG | B6: OUTCOME_TRAFFIC | C6: 49.98 | D6: 11656 | E6: 8162 | F6: =IFERROR(D6/E6,0) -> 1.4280814 | G6: 431 | H6: 351 | I6: =IFERROR(H6/D6,0) -> 0.030113246 | J6: =IFERROR(C6/H6,0) -> 0.14239316 | K6: =IFERROR(C6/D6*1000,0) -> 4.2879204 | L6: 2885 | M6: 3258 | N6: 8
A7: Totale | C7: =SUM(C5:C6) -> 347.69 | D7: =SUM(D5:D6) -> 120040 | E7: n.d. | G7: =SUM(G5:G6) -> 603 | H7: =SUM(H5:H6) -> 521 | I7: =IFERROR(H7/D7,0) -> 0.0043402199 | J7: =IFERROR(C7/H7,0) -> 0.66735125 | K7: =IFERROR(C7/D7*1000,0) -> 2.8964512 | L7: =SUM(L5:L6) -> 109263 | M7: =SUM(M5:M6) -> 109810 | N7: =SUM(N5:N6) -> 8
A8: La copertura non si somma tra campagne (le stesse persone possono averle viste entrambe).
A10: Campagna ancora attiva dopo il periodo del report
A11: Data | B11: Campagna | C11: Spesa (€) | D11: Impression
A12: 2026-10-03 | B12: [INTERAZIONI] Giugno 2026 | C12: 2.75 | D12: 881
A13: 2026-10-04 | B13: [INTERAZIONI] Giugno 2026 | C13: 2.43 | D13: 757
A14: 2026-10-05 | B14: [INTERAZIONI] Giugno 2026 | C14: 2.57 | D14: 844
A15: 2026-10-06 | B15: [INTERAZIONI] Giugno 2026 | C15: 2.25 | D15: 741
A16: 2026-10-07 | B16: [INTERAZIONI] Giugno 2026 | C16: 2.06 | D16: 681
A17: 2026-10-08 | B17: [INTERAZIONI] Giugno 2026 | C17: 2.26 | D17: 729
A18: 2026-10-09 | B18: [INTERAZIONI] Giugno 2026 | C18: 2.09 | D18: 629
A19: 2026-10-10 | B19: [INTERAZIONI] Giugno 2026 | C19: 2.37 | D19: 748
A20: 2026-10-11 | B20: [INTERAZIONI] Giugno 2026 | C20: 2.59 | D20: 765
A21: 2026-10-12 | B21: [INTERAZIONI] Giugno 2026 | C21: 1.92 | D21: 636
A22: 2026-10-13 | B22: [INTERAZIONI] Giugno 2026 | C22: 1.79 | D22: 639
A23: 2026-10-14 | B23: [INTERAZIONI] Giugno 2026 | C23: 1.75 | D23: 646
... A25: 2026-10-16 | B25: [INTERAZIONI] Giugno 2026 | C25: 1.05 | D25: 338
A26: Totale 3–16 ottobre | C26: =SUM(C12:C25) -> 29.83

Sheet ADV Inserzioni
A1: Meta Ads · risultati per inserzione
A2: Somma dei dati giornalieri per inserzione, tutte le piattaforme.
A4: Campagna | B4: Gruppo di inserzioni | C4: Inserzione | D4: Spesa (€) | E4: Impression | F4: Clic sul link | G4: CTR link | H4: Costo per clic link (€) | I4: Riproduzioni video 3s | J4: Video visti al 100%
A5: [INTERAZIONI] Giugno 2026 | B5: Vigonovo 30km, uomini 30-60 | C5: Reel brand 22.07 | D5: 97.71 | E5: 32866 | F5: 0 | G5: =IFERROR(F5/E5,0) -> 0 | H5: =IFERROR(D5/F5,0) -> 0 | I5: 32252 | J5: 6662
A6: [INTERAZIONI] Giugno 2026 | B6: Vigonovo 30km, uomini 30-60 | C6: Reel conto termico 27.05 | D6: 150 | E6: 57405 | F6: 135 | G6: =IFERROR(F6/E6,0) -> 0.0023517115 | H6: =IFERROR(D6/F6,0) -> 1.1111111 | I6: 56209 | J6: 11501
A7: [INTERAZIONI] Giugno 2026 | B7: Vigonovo 30km, uomini 30-60 | C7: Reel riscaldamento 25.06 | D7: 50 | E7: 18113 | F7: 35 | G7: =IFERROR(F7/E7,0) -> 0.0019323138 | H7: =IFERROR(D7/F7,0) -> 1.4285714 | I7: 17917 | J7: 17259
A8: [TRAFFICO] Reel IG | B8: Vigonovo, 30km, Uomo 30-60 | C8: Reel 2.09 | D8: 49.98 | E8: 11656 | F8: 351 | G8: =IFERROR(F8/E8,0) -> 0.030113246 | H8: =IFERROR(D8/F8,0) -> 0.14239316 | I8: 2885 | J8: 292

Sheet ADV Mese e piattaforma
A1: Meta Ads · per mese e piattaforma
A2: Dove sono state mostrate le inserzioni, mese per mese.
A4: Mese | B4: Campagna | C4: Piattaforma | D4: Spesa (€) | E4: Impression | F4: Copertura | G4: Clic sul link | H4: Riproduzioni video 3s
A5: Mag 2026 | B5: [INTERAZIONI] Giugno 2026 | C5: Audience Network | D5: 19.04 | E5: 4195 | F5: 1789 | G5: 11 | H5: 4170
A6: Mag 2026 | B6: [INTERAZIONI] Giugno 2026 | C6: Facebook | D6: 1.74 | E6: 1058 | F6: 985 | G6: 3 | H6: 362
A7: Mag 2026 | B7: [INTERAZIONI] Giugno 2026 | C7: Instagram | D7: 0.11 | E7: 74 | F7: 74 | G7: 0 | H7: 24
A8: Mag 2026 | B8: [INTERAZIONI] Giugno 2026 | C8: Threads | D8: 0 | E8: 1 | F8: 1 | G8: 0 | H8: 1
A9: Giu 2026 | B9: [INTERAZIONI] Giugno 2026 | C9: Audience Network | D9: 129.09 | E9: 52054 | F9: 10408 | G9: 121 | H9: 51640
A10: Giu 2026 | B10: [INTERAZIONI] Giugno 2026 | C10: Facebook | D10: 0.02 | E10: 22 | F10: 19 | G10: 0 | H10: 11
A11: Giu 2026 | B11: [INTERAZIONI] Giugno 2026 | C11: Instagram | D11: 0 | E11: 1 | F11: 1 | G11: 0 | H11: 1
A12: Lug 2026 | B12: [INTERAZIONI] Giugno 2026 | C12: Audience Network | D12: 49.82 | E12: 18028 | F12: 4025 | G12: 33 | H12: 17881
A13: Lug 2026 | B13: [INTERAZIONI] Giugno 2026 | C13: Facebook | D13: 0.18 | E13: 75 | F13: 73 | G13: 2 | H13: 33
A14: Lug 2026 | B14: [INTERAZIONI] Giugno 2026 | C14: Instagram | D14: 0 | E14: 6 | F14: 6 | G14: 0 | H14: 2
A15: Lug 2026 | B15: [INTERAZIONI] Giugno 2026 | C15: Threads | D15: 0 | E15: 4 | F15: 4 | G15: 0 | H15: 1
A16: Ago 2026 | B16: [INTERAZIONI] Giugno 2026 | C16: Audience Network | D16: 11.84 | E16: 4855 | F16: 1735 | G16: 0 | H16: 4767
... A24: Ott 2026 (solo 1 ott) | B24: [INTERAZIONI] Giugno 2026 | C24: Audience Network | D24: 2.32 | E24: 712 | F24: 340 | G24: 0 | H24: 706
A27: Totale per piattaforma
A28: Piattaforma | B28: Spesa (€) | C28: Impression | D28: Quota impression | E28: Clic sul link
A29: Audience Network | B29: =SUMIFS($D$5:$D$24,$C$5:$C$24,A29) -> 295.6 | C29: =SUMIFS($E$5:$E$24,$C$5:$C$24,A29) -> 107032 | D29: =IFERROR(C29/SUM($C$29:$C$32),0) -> 0.89163612 | E29: =SUMIFS($G$5:$G$24,$C$5:$C$24,A29) -> 165
A30: Facebook | B30: =SUMIFS($D$5:$D$24,$C$5:$C$24,A30) -> 39.07 | C30: =SUMIFS($E$5:$E$24,$C$5:$C$24,A30) -> 8474 | D30: =IFERROR(C30/SUM($C$29:$C$32),0) -> 0.070593136 | E30: =SUMIFS($G$5:$G$24,$C$5:$C$24,A30) -> 268
A31: Instagram | B31: =SUMIFS($D$5:$D$24,$C$5:$C$24,A31) -> 13.01 | C31: =SUMIFS($E$5:$E$24,$C$5:$C$24,A31) -> 4519 | D31: =IFERROR(C31/SUM($C$29:$C$32),0) -> 0.037645785 | E31: =SUMIFS($G$5:$G$24,$C$5:$C$24,A31) -> 88
A32: Threads | B32: =SUMIFS($D$5:$D$24,$C$5:$C$24,A32) -> 0.01 | C32: =SUMIFS($E$5:$E$24,$C$5:$C$24,A32) -> 15 | D32: =IFERROR(C32/SUM($C$29:$C$32),0) -> 0.00012495835 | E32: =SUMIFS($G$5:$G$24,$C$5:$C$24,A32) -> 0

Sheet ADV Giornaliero
A1: Meta Ads · dati giornalieri per inserzione e piattaforma
A2: Righe presenti solo nei giorni con consegna.
A4: Data | B4: Campagna | C4: Inserzione | D4: Piattaforma | E4: Spesa (€) | F4: Impression | G4: Copertura | H4: Clic (tutti) | I4: Clic sul link | J4: Riproduzioni video 3s | K4: Stato campagna (oggi)
A5: 2026-05-28 | B5: [INTERAZIONI] Giugno 2026 | C5: Reel conto termico 27.05 | D5: Audience Network | E5: 0.55 | F5: 95 | G5: 36 | H5: 0 | I5: 0 | J5: 95 | K5: ACTIVE
A6: 2026-05-28 | B6: [INTERAZIONI] Giugno 2026 | C6: Reel conto termico 27.05 | D6: Facebook | E6: 0.68 | F6: 457 | G6: 433 | H6: 0 | I6: 0 | J6: 145 | K6: ACTIVE
A7: 2026-05-28 | B7: [INTERAZIONI] Giugno 2026 | C7: Reel conto termico 27.05 | D7: Instagram | E7: 0.07 | F7: 47 | G7: 47 | H7: 0 | I7: 0 | J7: 15 | K7: ACTIVE
A8: 2026-05-29 | B8: [INTERAZIONI] Giugno 2026 | C8: Reel conto termico 27.05 | D8: Audience Network | E8: 5.94 | F8: 1285 | G8: 685 | H8: 1 | I8: 1 | J8: 1272 | K8: ACTIVE
A9: 2026-05-29 | B9: [INTERAZIONI] Giugno 2026 | C9: Reel conto termico 27.05 | D9: Facebook | E9: 1.06 | F9: 592 | G9: 544 | H9: 5 | I9: 3 | J9: 212 | K9: ACTIVE
A10: 2026-05-29 | B10: [INTERAZIONI] Giugno 2026 | C10: Reel conto termico 27.05 | D10: Instagram | E10: 0.04 | F10: 27 | G10: 27 | H10: 0 | I10: 0 | J10: 9 | K10: ACTIVE
A11: 2026-05-29 | B11: [INTERAZIONI] Giugno 2026 | C11: Reel conto termico 27.05 | D11: Threads | E11: 0 | F11: 1 | G11: 1 | H11: 0 | I11: 0 | J11: 1 | K11: ACTIVE
A12: 2026-05-30 | B12: [INTERAZIONI] Giugno 2026 | C12: Reel conto termico 27.05 | D12: Audience Network | E12: 5.52 | F12: 1318 | G12: 660 | H12: 3 | I12: 3 | J12: 1310 | K12: ACTIVE
A13: 2026-05-30 | B13: [INTERAZIONI] Giugno 2026 | C13: Reel conto termico 27.05 | D13: Facebook | E13: 0 | F13: 4 | G13: 4 | H13: 0 | I13: 0 | J13: 3 | K13: ACTIVE
A14: 2026-05-31 | B14: [INTERAZIONI] Giugno 2026 | C14: Reel conto termico 27.05 | D14: Audience Network | E14: 7.03 | F14: 1497 | G14: 697 | H14: 6 | I14: 7 | J14: 1493 | K14: ACTIVE
A15: 2026-05-31 | B15: [INTERAZIONI] Giugno 2026 | C15: Reel conto termico 27.05 | D15: Facebook | E15: 0 | F15: 5 | G15: 5 | H15: 0 | I15: 0 | J15: 2 | K15: ACTIVE
A16: 2026-06-01 | B16: [INTERAZIONI] Giugno 2026 | C16: Reel conto termico 27.05 | D16: Audience Network | E16: 7.83 | F16: 2077 | G16: 887 | H16: 5 | I16: 5 | J16: 2071 | K16: ACTIVE
... A173: 2026-10-01 | B173: [INTERAZIONI] Giugno 2026 | C173: Reel brand 22.07 | D173: Audience Network | E173: 2.32 | F173: 712 | G173: 340 | H173: 0 | I173: 0 | J173: 706 | K173: ACTIVE

Sheet FB Giornaliero
A1: Pagina Facebook Gen&Sys Srl · dati giornalieri
A2: Fonte: Windsor.ai, connettore Facebook Organic. Le impression sponsorizzate sono quelle generate dalle inserzioni.
A4: Data | B4: Impression | C4: Impression organiche | D4: Impression sponsorizzate | E4: Interazioni con i post | F4: Nuovi follower | G4: Follower totali | H4: Visite alla pagina
A5: 2026-01-01 | B5: 0 | C5: 0 | D5: 0 | E5: 0 | F5: 0 | G5: 0 | H5: 0
A6: 2026-01-02 | B6: 0 | C6: 0 | D6: 0 | E6: 0 | F6: 0 | G6: 0 | H6: 0
A7: 2026-01-03 | B7: 0 | C7: 0 | D7: 0 | E7: 0 | F7: 0 | G7: 0 | H7: 0
A8: 2026-01-04 | B8: 0 | C8: 0 | D8: 0 | E8: 0 | F8: 0 | G8: 0 | H8: 0
A9: 2026-01-05 | B9: 0 | C9: 0 | D9: 0 | E9: 0 | F9: 0 | G9: 0 | H9: 0
A10: 2026-01-06 | B10: 0 | C10: 0 | D10: 0 | E10: 0 | F10: 0 | G10: 0 | H10: 0
A11: 2026-01-07 | B11: 0 | C11: 0 | D11: 0 | E11: 0 | F11: 0 | G11: 0 | H11: 0
A12: 2026-01-08 | B12: 0 | C12: 0 | D12: 0 | E12: 0 | F12: 0 | G12: 0 | H12: 0
A13: 2026-01-09 | B13: 0 | C13: 0 | D13: 0 | E13: 0 | F13: 0 | G13: 0 | H13: 0
A14: 2026-01-10 | B14: 0 | C14: 0 | D14: 0 | E14: 0 | F14: 0 | G14: 0 | H14: 0
A15: 2026-01-11 | B15: 0 | C15: 0 | D15: 0 | E15: 0 | F15: 0 | G15: 0 | H15: 0
A16: 2026-01-12 | B16: 0 | C16: 0 | D16: 0 | E16: 0 | F16: 0 | G16: 0 | H16: 0
... A278: 2026-10-01 | B278: 0 | C278: 0 | D278: 0 | E278: 0 | F278: 0 | G278: 19 | H278: 2

Sheet FB Mensile
A1: Pagina Facebook · totali mensili
A2: Calcolati dal foglio FB Giornaliero. Ottobre comprende solo il 1° ottobre.
A4: Mese | B4: Impression | C4: Impression organiche | D4: Impression sponsorizzate | E4: Interazioni con i post | F4: Nuovi follower | G4: Visite alla pagina | H4: Quota sponsorizzata
A5: 2026-01 | B5: =SUMPRODUCT((LEFT('FB Giornaliero'!$A$5:$A$278,7)=$A5)*'FB Giornaliero'!B$5:B$278) -> 0 | C5: =SUMPRODUCT((LEFT('FB Giornaliero'!$A$5:$A$278,7)=$A5)*'FB Giornaliero'!C$5:C$278) -> 0 | D5: =SUMPRODUCT((LEFT('FB Giornaliero'!$A$5:$A$278,7)=$A5)*'FB Giornaliero'!D$5:D$278) -> 0 | E5: =SUMPRODUCT((LEFT('FB Giornaliero'!$A$5:$A$278,7)=$A5)*'FB Giornaliero'!E$5:E$278) -> 0 | F5: =SUMPRODUCT((LEFT('FB Giornaliero'!$A$5:$A$278,7)=$A5)*'FB Giornaliero'!F$5:F$278) -> 1 | G5: =SUMPRODUCT((LEFT('FB Giornaliero'!$A$5:$A$278,7)=$A5)*'FB Giornaliero'!H$5:H$278) -> 11 | H5: =IFERROR(D5/B5,0) -> 0
A6: 2026-02 | B6: =SUMPRODUCT((LEFT('FB Giornaliero'!$A$5:$A$278,7)=$A6)*'FB Giornaliero'!B$5:B$278) -> 170 | C6: =SUMPRODUCT((LEFT('FB Giornaliero'!$A$5:$A$278,7)=$A6)*'FB Giornaliero'!C$5:C$278) -> 170 | D6: =SUMPRODUCT((LEFT('FB Giornaliero'!$A$5:$A$278,7)=$A6)*'FB Giornaliero'!D$5:D$278) -> 0 | E6: =SUMPRODUCT((LEFT('FB Giornaliero'!$A$5:$A$278,7)=$A6)*'FB Giornaliero'!E$5:E$278) -> 28 | F6: =SUMPRODUCT((LEFT('FB Giornaliero'!$A$5:$A$278,7)=$A6)*'FB Giornaliero'!F$5:F$278) -> 7 | G6: =SUMPRODUCT((LEFT('FB Giornaliero'!$A$5:$A$278,7)=$A6)*'FB Giornaliero'!H$5:H$278) -> 23 | H6: =IFERROR(D6/B6,0) -> 0
A7: 2026-03 | B7: =SUMPRODUCT((LEFT('FB Giornaliero'!$A$5:$A$278,7)=$A7)*'FB Giornaliero'!B$5:B$278) -> 97 | C7: =SUMPRODUCT((LEFT('FB Giornaliero'!$A$5:$A$278,7)=$A7)*'FB Giornaliero'!C$5:C$278) -> 97 | D7: =SUMPRODUCT((LEFT('FB Giornaliero'!$A$5:$A$278,7)=$A7)*'FB Giornaliero'!D$5:D$278) -> 0 | E7: =SUMPRODUCT((LEFT('FB Giornaliero'!$A$5:$A$278,7)=$A7)*'FB Giornaliero'!E$5:E$278) -> 15 | F7: =SUMPRODUCT((LEFT('FB Giornaliero'!$A$5:$A$278,7)=$A7)*'FB Giornaliero'!F$5:F$278) -> 1 | G7: =SUMPRODUCT((LEFT('FB Giornaliero'!$A$5:$A$278,7)=$A7)*'FB Giornaliero'!H$5:H$278) -> 18 | H7: =IFERROR(D7/B7,0) -> 0
A8: 2026-04 | B8: =SUMPRODUCT((LEFT('FB Giornaliero'!$A$5:$A$278,7)=$A8)*'FB Giornaliero'!B$5:B$278) -> 80 | C8: =SUMPRODUCT((LEFT('FB Giornaliero'!$A$5:$A$278,7)=$A8)*'FB Giornaliero'!C$5:C$278) -> 80 | D8: =SUMPRODUCT((LEFT('FB Giornaliero'!$A$5:$A$278,7)=$A8)*'FB Giornaliero'!D$5:D$278) -> 0 | E8: =SUMPRODUCT((LEFT('FB Giornaliero'!$A$5:$A$278,7)=$A8)*'FB Giornaliero'!E$5:E$278) -> 2 | F8: =SUMPRODUCT((LEFT('FB Giornaliero'!$A$5:$A$278,7)=$A8)*'FB Giornaliero'!F$5:F$278) -> 1 | G8: =SUMPRODUCT((LEFT('FB Giornaliero'!$A$5:$A$278,7)=$A8)*'FB Giornaliero'!H$5:H$278) -> 3 | H8: =IFERROR(D8/B8,0) -> 0
A9: 2026-05 | B9: =SUMPRODUCT((LEFT('FB Giornaliero'!$A$5:$A$278,7)=$A9)*'FB Giornaliero'!B$5:B$278) -> 1375 | C9: =SUMPRODUCT((LEFT('FB Giornaliero'!$A$5:$A$278,7)=$A9)*'FB Giornaliero'!C$5:C$278) -> 214 | D9: =SUMPRODUCT((LEFT('FB Giornaliero'!$A$5:$A$278,7)=$A9)*'FB Giornaliero'!D$5:D$278) -> 1161 | E9: =SUMPRODUCT((LEFT('FB Giornaliero'!$A$5:$A$278,7)=$A9)*'FB Giornaliero'!E$5:E$278) -> 10 | F9: =SUMPRODUCT((LEFT('FB Giornaliero'!$A$5:$A$278,7)=$A9)*'FB Giornaliero'!F$5:F$278) -> 0 | G9: =SUMPRODUCT((LEFT('FB Giornaliero'!$A$5:$A$278,7)=$A9)*'FB Giornaliero'!H$5:H$278) -> 2 | H9: =IFERROR(D9/B9,0) -> 0.84436364
A10: 2026-06 | B10: =SUMPRODUCT((LEFT('FB Giornaliero'!$A$5:$A$278,7)=$A10)*'FB Giornaliero'!B$5:B$278) -> 359 | C10: =SUMPRODUCT((LEFT('FB Giornaliero'!$A$5:$A$278,7)=$A10)*'FB Giornaliero'!C$5:C$278) -> 338 | D10: =SUMPRODUCT((LEFT('FB Giornaliero'!$A$5:$A$278,7)=$A10)*'FB Giornaliero'!D$5:D$278) -> 21 | E10: =SUMPRODUCT((LEFT('FB Giornaliero'!$A$5:$A$278,7)=$A10)*'FB Giornaliero'!E$5:E$278) -> 2 | F10: =SUMPRODUCT((LEFT('FB Giornaliero'!$A$5:$A$278,7)=$A10)*'FB Giornaliero'!F$5:F$278) -> 1 | G10: =SUMPRODUCT((LEFT('FB Giornaliero'!$A$5:$A$278,7)=$A10)*'FB Giornaliero'!H$5:H$278) -> 9 | H10: =IFERROR(D10/B10,0) -> 0.058495822
A11: 2026-07 | B11: =SUMPRODUCT((LEFT('FB Giornaliero'!$A$5:$A$278,7)=$A11)*'FB Giornaliero'!B$5:B$278) -> 364 | C11: =SUMPRODUCT((LEFT('FB Giornaliero'!$A$5:$A$278,7)=$A11)*'FB Giornaliero'!C$5:C$278) -> 276 | D11: =SUMPRODUCT((LEFT('FB Giornaliero'!$A$5:$A$278,7)=$A11)*'FB Giornaliero'!D$5:D$278) -> 88 | E11: =SUMPRODUCT((LEFT('FB Giornaliero'!$A$5:$A$278,7)=$A11)*'FB Giornaliero'!E$5:E$278) -> 8 | F11: =SUMPRODUCT((LEFT('FB Giornaliero'!$A$5:$A$278,7)=$A11)*'FB Giornaliero'!F$5:F$278) -> 0 | G11: =SUMPRODUCT((LEFT('FB Giornaliero'!$A$5:$A$278,7)=$A11)*'FB Giornaliero'!H$5:H$278) -> 13 | H11: =IFERROR(D11/B11,0) -> 0.24175824
A12: 2026-08 | B12: =SUMPRODUCT((LEFT('FB Giornaliero'!$A$5:$A$278,7)=$A12)*'FB Giornaliero'!B$5:B$278) -> 117 | C12: =SUMPRODUCT((LEFT('FB Giornaliero'!$A$5:$A$278,7)=$A12)*'FB Giornaliero'!C$5:C$278) -> 24 | D12: =SUMPRODUCT((LEFT('FB Giornaliero'!$A$5:$A$278,7)=$A12)*'FB Giornaliero'!D$5:D$278) -> 93 | E12: =SUMPRODUCT((LEFT('FB Giornaliero'!$A$5:$A$278,7)=$A12)*'FB Giornaliero'!E$5:E$278) -> 4 | F12: =SUMPRODUCT((LEFT('FB Giornaliero'!$A$5:$A$278,7)=$A12)*'FB Giornaliero'!F$5:F$278) -> 0 | G12: =SUMPRODUCT((LEFT('FB Giornaliero'!$A$5:$A$278,7)=$A12)*'FB Giornaliero'!H$5:H$278) -> 3 | H12: =IFERROR(D12/B12,0) -> 0.79487179
A13: 2026-09 | B13: =SUMPRODUCT((LEFT('FB Giornaliero'!$A$5:$A$278,7)=$A13)*'FB Giornaliero'!B$5:B$278) -> 10825 | C13: =SUMPRODUCT((LEFT('FB Giornaliero'!$A$5:$A$278,7)=$A13)*'FB Giornaliero'!C$5:C$278) -> 663 | D13: =SUMPRODUCT((LEFT('FB Giornaliero'!$A$5:$A$278,7)=$A13)*'FB Giornaliero'!D$5:D$278) -> 10162 | E13: =SUMPRODUCT((LEFT('FB Giornaliero'!$A$5:$A$278,7)=$A13)*'FB Giornaliero'!E$5:E$278) -> 314 | F13: =SUMPRODUCT((LEFT('FB Giornaliero'!$A$5:$A$278,7)=$A13)*'FB Giornaliero'!F$5:F$278) -> 8 | G13: =SUMPRODUCT((LEFT('FB Giornaliero'!$A$5:$A$278,7)=$A13)*'FB Giornaliero'!H$5:H$278) -> 937 | H13: =IFERROR(D13/B13,0) -> 0.93875289
A14: 2026-10 | B14: =SUMPRODUCT((LEFT('FB Giornaliero'!$A$5:$A$278,7)=$A14)*'FB Giornaliero'!B$5:B$278) -> 0 | C14: =SUMPRODUCT((LEFT('FB Giornaliero'!$A$5:$A$278,7)=$A14)*'FB Giornaliero'!C$5:C$278) -> 0 | D14: =SUMPRODUCT((LEFT('FB Giornaliero'!$A$5:$A$278,7)=$A14)*'FB Giornaliero'!D$5:D$278) -> 0 | E14: =SUMPRODUCT((LEFT('FB Giornaliero'!$A$5:$A$278,7)=$A14)*'FB Giornaliero'!E$5:E$278) -> 0 | F14: =SUMPRODUCT((LEFT('FB Giornaliero'!$A$5:$A$278,7)=$A14)*'FB Giornaliero'!F$5:F$278) -> 0 | G14: =SUMPRODUCT((LEFT('FB Giornaliero'!$A$5:$A$278,7)=$A14)*'FB Giornaliero'!H$5:H$278) -> 2 | H14: =IFERROR(D14/B14,0) -> 0
A15: Totale | B15: =SUM(B5:B14) -> 13387 | C15: =SUM(C5:C14) -> 1862 | D15: =SUM(D5:D14) -> 11525 | E15: =SUM(E5:E14) -> 383 | F15: =SUM(F5:F14) -> 19 | G15: =SUM(G5:G14) -> 1021 | H15: =IFERROR(D15/B15,0) -> 0.86090984

Sheet FB Post
A1: Pagina Facebook · post del periodo
A2: Le impression dei post includono quelle sponsorizzate quando il post è stato promosso.
A4: Data | B4: Formato | C4: Testo | D4: Impression | E4: Interazioni | F4: Reazioni | G4: Commenti | H4: Condivisioni | I4: Clic | J4: Link
A5: 2026-02-18 | B5: Foto profilo | D5: 45 | E5: 4 | F5: 4 | G5: 0 | H5: 0 | I5: 4 | J5: https://www.facebook.com/photo.php?fbid=122113496637206039&set=a.122104629159206039&type=3
A6: 2026-02-18 | B6: Foto copertina | D6: 46 | E6: 0 | F6: 0 | G6: 0 | H6: 0 | I6: 0 | J6: https://www.facebook.com/122124922155206039/posts/2006967940207117?substory_index=2006967940207117
A7: 2026-02-19 | B7: Carosello | C7: Gen&Sys è un’azienda a conduzione familiare che da oltre 15 anni lavora a fianco degli installatori. Non siamo un semplice punto di fornitura, ma un partner tecnico che affianca ogni progetto, dalla scelta dell’impianto alla gestione delle pratiche. 049 9802495 | www.genesyssrl.com | info@genesyssrl.com 📍Via Sagredo 21, Vigonovo (VE) #genesys #genesyssrl #termoidraulica #riscaldamento #climatizzazione #pompedicalore #daikin #lgelectronics #chaffoteaux #bwt #aristonthermogroup | D7: 76 | E7: 4 | F7: 4 | G7: 0 | H7: 0 | I7: 2 | J7: https://www.facebook.com/122124922155206039/posts/122113670541206039
A8: 2026-02-23 | B8: Foto | C8: 📍La nostra sede - Vigonovo (VE) Un punto di riferimento per gli installatori del territorio. Qui lavoriamo ogni giorno per affiancare chi opera nel settore impiantistico, con supporto tecnico, consulenza e gestione delle pratiche. 049 9802495 | info@genesyssrl.com #genesys #genesyssrl #termoidraulica #riscaldamento #climatizzazione #pompedicalore #daikin #lgelectronics #chaffoteaux #bwt #aristonthermogroup | D8: 43 | E8: 6 | F8: 5 | G8: 0 | H8: 1 | I8: 0 | J8: https://www.facebook.com/122124922155206039/posts/122114389893206039
A9: 2026-02-25 | B9: Carosello | C9: Ogni impianto ha esigenze diverse. Per questo noi di Gen&Sys proponiamo una gamma completa di soluzioni impiantistiche, selezionate per adattarsi a contesti, configurazioni e necessità differenti. Non un unico prodotto, ma più possibilità tra cui scegliere, con il supporto tecnico giusto per individuare quella corretta. 049 9802495 | www.genesyssrl.com | info@genesyssrl.com 📍Via Sagredo 21, Vigonovo (VE) #genesys #genesyssrl #termoidraulica #riscaldamento #climatizzazione #pompedicalore #daikin #lgelectronics #chaffoteaux #bwt #aristonthermogroup | D9: 42 | E9: 6 | F9: 5 | G9: 0 | H9: 1 | I9: 0 | J9: https://www.facebook.com/122124922155206039/posts/122114727819206039
A10: 2026-02-27 | B10: Carosello | C10: La differenza non è solo in cosa fornisci, ma nel supporto che dai. Gen&Sys affianca gli installatori con un servizio completo, pensato per semplificare il lavoro e ridurre le complessità operative. Dalla consulenza tecnica alla gestione delle pratiche, siamo presenti in ogni fase. 049 9802495 | www.genesyssrl.com | info@genesyssrl.com 📍Via Sagredo 21, Vigonovo (VE) #genesys #genesyssrl #termoidraulica #riscaldamento #climatizzazione #pompedicalore #daikin #lgelectronics #chaffoteaux #bwt #aristonthermogroup | D10: 39 | E10: 6 | F10: 5 | G10: 0 | H10: 1 | I10: 0 | J10: https://www.facebook.com/122124922155206039/posts/122115094653206039
A11: 2026-03-02 | B11: Carosello | C11: ll 𝐂𝐎𝐍𝐓𝐎 𝐓𝐄𝐑𝐌𝐈𝐂𝐎 𝟑.𝟎 è la nuova misura di incentivo statale che sostiene interventi per l’efficienza energetica e la produzione di calore da fonti rinnovabili, come l’installazione di pompe di calore ad alta efficienza. Il contributo è a fondo perduto e può coprire fino al 65% delle spese ammissibili per privati e imprese, con casi particolari fino al 100% per edifici pubblici. La misura è uno strumento concreto per ridurre l’investimento iniziale e accelerare la transizione verso soluzioni più efficienti. Noi di Gen&Sys ci occupiamo della gestione completa della pratica, fornendo tutta la documentazione e le certificazioni necessarie. 049 9802495 | www.genesyssrl.com | info@genesyssrl.com 📍Via Sagredo 21, Vigonovo (VE) #genesys #genesyssrl #termoidraulica #riscaldamento #climatizzazione #pompedicalore #daikin #lgelectronics #chaffoteaux #bwt #aristonthermogroup | D11: 44 | E11: 5 | F11: 4 | G11: 0 | H11: 1 | I11: 0 | J11: https://www.facebook.com/122124922155206039/posts/122115560337206039
A12: 2026-03-05 | B12: Foto | C12: Ogni impianto ha esigenze diverse. Per questo Gen&Sys propone soluzioni di 6 brand selezionati, così da offrire alternative concrete in base a contesto, configurazione e obiettivi del cliente finale. Avere più possibilità significa poter scegliere la soluzione più adatta, non la più standard. Il prodotto giusto nasce da una valutazione attenta. A supporto delle scelte impiantistiche, sempre. 049 9802495 | www.genesyssrl.com | info@genesyssrl.com 📍Via Sagredo 21, Vigonovo (VE) #genesys #genesyssrl #termoidraulica #riscaldamento #climatizzazione #pompedicalore #daikin #lgelectronics #chaffoteaux #bwt #aristonthermogroup | D12: 48 | E12: 3 | F12: 3 | G12: 0 | H12: 0 | I12: 1 | J12: https://www.facebook.com/122124922155206039/posts/122116008753206039
A13: 2026-04-07 | B13: Foto | C13: 📍Dove si trova la nostra sede? In Via Sagredo 21, a Vigonovo. Facilmente raggiungibile dalle principali direttrici tra Padova, Venezia e la Riviera del Brenta 049 9802495 | info@genesyssrl.com #genesys #genesyssrl #termoidraulica #riscaldamento #climatizzazione #pompedicalore #daikin #lgelectronics #chaffoteaux #bwt #aristonthermogroup | D13: 33 | E13: 2 | F13: 2 | G13: 0 | H13: 0 | I13: 0 | J13: https://www.facebook.com/122124922155206039/posts/122120792103206039
A14: 2026-04-15 | B14: Carosello | C14: La pompa di calore non è sempre la soluzione giusta. Dipende dall’edificio, dall’impianto esistente e dagli obiettivi energetici. Capire quando conviene installarla – e quando è meglio valutare un sistema diverso – è il primo passo per un impianto che funzioni davvero nel tempo. La scelta parte dall’analisi, non dalla tendenza. 049 9802495 | info@genesyssrl.com #genesys #genesyssrl #termoidraulica #riscaldamento #climatizzazione #pompedicalore #daikin #lgelectronics #chaffoteaux #bwt #aristonthermogroup | D14: 28 | E14: 1 | F14: 1 | G14: 0 | H14: 0 | I14: 0 | J14: https://www.facebook.com/122124922155206039/posts/122121785325206039
A15: 2026-04-22 | B15: Reel | C15: Gen&Sys si racconta anche attraverso i numeri. Esperienza, progetti realizzati, collaborazioni costruite nel tempo e competenze tecniche dedicate: sono questi gli elementi che definiscono il nostro percorso. 049 9802495 | info@genesyssrl.com #genesys #genesyssrl #termoidraulica #riscaldamento #climatizzazione #pompedicalore #daikin #lgelectronics #chaffoteaux #bwt #aristonthermogroup | D15: 84 | E15: 0 | F15: 0 | G15: 0 | H15: 0 | I15: 0 | J15: https://www.facebook.com/reel/944101568535301/
A16: 2026-05-13 | B16: Carosello | C16: Scegliere una pompa di calore non significa solo guardare i kW dichiarati. Il dimensionamento corretto parte da carico termico reale, regime di funzionamento, terminali esistenti e obiettivi energetici dell’edificio. Un impianto sovradimensionato lavora male. Uno sottodimensionato non garantisce comfort. La differenza sta nella valutazione tecnica iniziale. 049 9802495 | info@genesyssrl.com | D16: 37 | E16: 0 | F16: 0 | G16: 0 | H16: 0 | I16: 0 | J16: https://www.facebook.com/122124922155206039/posts/122125123383206039
A17: 2026-05-27 | B17: Reel | C17: Conto Termico 3.0 un’opportunità concreta per rendere più efficiente la tua casa o la tua azienda. Il nuovo incentivo sostiene interventi per migliorare l’efficienza energetica e favorire l’utilizzo di fonti rinnovabili, con contributi fino al 65% delle spese ammissibili. Caldaie, pompe di calore, solare termico e altri interventi possono diventare oggi un investimento più accessibile, con benefici immediati su consumi, comfort e sostenibilità. Approfitta del Conto Termico 3.0 e trasforma l’efficienza in valore. 📩 Contattaci per scoprire quali interventi possono rientrare nell’incentivo. 049 9802495 | info@genesyssrl.com | D17: 1407 | E17: 0 | F17: 0 | G17: 0 | H17: 0 | I17: 137 | J17: https://www.facebook.com/reel/980906034641896/
A18: 2026-06-11 | B18: Carosello | C18: Ogni progetto ha esigenze diverse. Per questo Gen&Sys non propone pacchetti standard, ma soluzioni impiantistiche pensate in base al contesto, agli obiettivi e alle necessità del cliente. Dalle caldaie a gas ai sistemi ibridi, dalle pompe di calore alla climatizzazione VRV/VRF, seguiamo impianti in ambito domestico, civile e industriale con un approccio flessibile e concreto. Perché un impianto efficiente nasce prima di tutto da una progettazione adatta alla realtà in cui verrà installato. 📩 Raccontaci le tue esigenze: ti aiutiamo a trovare la soluzione più adatta. 049 9802495 | info@genesyssrl.com | D18: 26 | E18: 0 | F18: 0 | G18: 0 | H18: 0 | I18: 0 | J18: https://www.facebook.com/122124922155206039/posts/122128087569206039
... A33: 2026-09-30 | B33: Carosello | C33: Due preventivi per lo stesso edificio possono arrivare a dimensionamenti diversi. Il punto non è capire semplicemente chi propone più o meno kW, ma da quali dati nasce quel numero. Un dimensionamento serio deve poter essere spiegato: dispersioni, condizioni di progetto, terminali e temperature di lavoro. Perché una scelta tecnica è davvero utile quando se ne comprende il perché. 049 9802495 | info@genesyssrl.com | D33: 5 | E33: 0 | F33: 0 | G33: 0 | H33: 0 | I33: 0 | J33: https://www.facebook.com/122124922155206039/posts/122141392947206039

Sheet IG Giornaliero
A1: Profilo Instagram @genesys_srl · dati giornalieri
A2: Fonte: Windsor.ai, connettore Instagram. Instagram non separa organico e sponsorizzato in questi dati.
A4: Data | B4: Copertura | C4: Visualizzazioni | D4: Account che hanno interagito | E4: Interazioni totali | F4: Mi piace | G4: Commenti | H4: Salvataggi | I4: Condivisioni | J4: Tap su contatti
A5: 2026-01-01 | B5: 0 | C5: 0 | D5: 0 | E5: 0 | F5: 0 | G5: 0 | H5: 0 | I5: 0 | J5: 0
A6: 2026-01-02 | B6: 0 | C6: 0 | D6: 0 | E6: 0 | F6: 0 | G6: 0 | H6: 0 | I6: 0 | J6: 0
A7: 2026-01-03 | B7: 0 | C7: 0 | D7: 0 | E7: 0 | F7: 0 | G7: 0 | H7: 0 | I7: 0 | J7: 0
A8: 2026-01-04 | B8: 0 | C8: 0 | D8: 0 | E8: 0 | F8: 0 | G8: 0 | H8: 0 | I8: 0 | J8: 0
A9: 2026-01-05 | B9: 0 | C9: 0 | D9: 0 | E9: 0 | F9: 0 | G9: 0 | H9: 0 | I9: 0 | J9: 0
A10: 2026-01-06 | B10: 0 | C10: 0 | D10: 0 | E10: 0 | F10: 0 | G10: 0 | H10: 0 | I10: 0 | J10: 0
A11: 2026-01-07 | B11: 0 | C11: 0 | D11: 0 | E11: 0 | F11: 0 | G11: 0 | H11: 0 | I11: 0 | J11: 0
A12: 2026-01-08 | B12: 0 | C12: 0 | D12: 0 | E12: 0 | F12: 0 | G12: 0 | H12: 0 | I12: 0 | J12: 0
A13: 2026-01-09 | B13: 0 | C13: 0 | D13: 0 | E13: 0 | F13: 0 | G13: 0 | H13: 0 | I13: 0 | J13: 0
A14: 2026-01-10 | B14: 0 | C14: 0 | D14: 0 | E14: 0 | F14: 0 | G14: 0 | H14: 0 | I14: 0 | J14: 0
A15: 2026-01-11 | B15: 0 | C15: 0 | D15: 0 | E15: 0 | F15: 0 | G15: 0 | H15: 0 | I15: 0 | J15: 0
A16: 2026-01-12 | B16: 0 | C16: 0 | D16: 0 | E16: 0 | F16: 0 | G16: 0 | H16: 0 | I16: 0 | J16: 0
... A278: 2026-10-01 | B278: 14 | C278: 38 | D278: 0 | E278: 0 | F278: 0 | G278: 0 | H278: 0 | I278: 0 | J278: 0

Sheet IG Mensile
A1: Profilo Instagram · totali mensili
A2: La copertura mensile è la somma della copertura giornaliera, non il numero di persone uniche.
A4: Mese | B4: Copertura (somma giornaliera) | C4: Visualizzazioni | D4: Interazioni totali | E4: Mi piace | F4: Salvataggi | G4: Condivisioni
A5: 2026-01 | B5: =SUMPRODUCT((LEFT('IG Giornaliero'!$A$5:$A$278,7)=$A5)*'IG Giornaliero'!B$5:B$278) -> 0 | C5: =SUMPRODUCT((LEFT('IG Giornaliero'!$A$5:$A$278,7)=$A5)*'IG Giornaliero'!C$5:C$278) -> 0 | D5: =SUMPRODUCT((LEFT('IG Giornaliero'!$A$5:$A$278,7)=$A5)*'IG Giornaliero'!E$5:E$278) -> 0 | E5: =SUMPRODUCT((LEFT('IG Giornaliero'!$A$5:$A$278,7)=$A5)*'IG Giornaliero'!F$5:F$278) -> 0 | F5: =SUMPRODUCT((LEFT('IG Giornaliero'!$A$5:$A$278,7)=$A5)*'IG Giornaliero'!H$5:H$278) -> 0 | G5: =SUMPRODUCT((LEFT('IG Giornaliero'!$A$5:$A$278,7)=$A5)*'IG Giornaliero'!I$5:I$278) -> 0
A6: 2026-02 | B6: =SUMPRODUCT((LEFT('IG Giornaliero'!$A$5:$A$278,7)=$A6)*'IG Giornaliero'!B$5:B$278) -> 141 | C6: =SUMPRODUCT((LEFT('IG Giornaliero'!$A$5:$A$278,7)=$A6)*'IG Giornaliero'!C$5:C$278) -> 348 | D6: =SUMPRODUCT((LEFT('IG Giornaliero'!$A$5:$A$278,7)=$A6)*'IG Giornaliero'!E$5:E$278) -> 22 | E6: =SUMPRODUCT((LEFT('IG Giornaliero'!$A$5:$A$278,7)=$A6)*'IG Giornaliero'!F$5:F$278) -> 18 | F6: =SUMPRODUCT((LEFT('IG Giornaliero'!$A$5:$A$278,7)=$A6)*'IG Giornaliero'!H$5:H$278) -> 0 | G6: =SUMPRODUCT((LEFT('IG Giornaliero'!$A$5:$A$278,7)=$A6)*'IG Giornaliero'!I$5:I$278) -> 2
A7: 2026-03 | B7: =SUMPRODUCT((LEFT('IG Giornaliero'!$A$5:$A$278,7)=$A7)*'IG Giornaliero'!B$5:B$278) -> 76 | C7: =SUMPRODUCT((LEFT('IG Giornaliero'!$A$5:$A$278,7)=$A7)*'IG Giornaliero'!C$5:C$278) -> 213 | D7: =SUMPRODUCT((LEFT('IG Giornaliero'!$A$5:$A$278,7)=$A7)*'IG Giornaliero'!E$5:E$278) -> 11 | E7: =SUMPRODUCT((LEFT('IG Giornaliero'!$A$5:$A$278,7)=$A7)*'IG Giornaliero'!F$5:F$278) -> 8 | F7: =SUMPRODUCT((LEFT('IG Giornaliero'!$A$5:$A$278,7)=$A7)*'IG Giornaliero'!H$5:H$278) -> 0 | G7: =SUMPRODUCT((LEFT('IG Giornaliero'!$A$5:$A$278,7)=$A7)*'IG Giornaliero'!I$5:I$278) -> 1
A8: 2026-04 | B8: =SUMPRODUCT((LEFT('IG Giornaliero'!$A$5:$A$278,7)=$A8)*'IG Giornaliero'!B$5:B$278) -> 65 | C8: =SUMPRODUCT((LEFT('IG Giornaliero'!$A$5:$A$278,7)=$A8)*'IG Giornaliero'!C$5:C$278) -> 204 | D8: =SUMPRODUCT((LEFT('IG Giornaliero'!$A$5:$A$278,7)=$A8)*'IG Giornaliero'!E$5:E$278) -> 16 | E8: =SUMPRODUCT((LEFT('IG Giornaliero'!$A$5:$A$278,7)=$A8)*'IG Giornaliero'!F$5:F$278) -> 14 | F8: =SUMPRODUCT((LEFT('IG Giornaliero'!$A$5:$A$278,7)=$A8)*'IG Giornaliero'!H$5:H$278) -> 0 | G8: =SUMPRODUCT((LEFT('IG Giornaliero'!$A$5:$A$278,7)=$A8)*'IG Giornaliero'!I$5:I$278) -> 1
A9: 2026-05 | B9: =SUMPRODUCT((LEFT('IG Giornaliero'!$A$5:$A$278,7)=$A9)*'IG Giornaliero'!B$5:B$278) -> 306 | C9: =SUMPRODUCT((LEFT('IG Giornaliero'!$A$5:$A$278,7)=$A9)*'IG Giornaliero'!C$5:C$278) -> 369 | D9: =SUMPRODUCT((LEFT('IG Giornaliero'!$A$5:$A$278,7)=$A9)*'IG Giornaliero'!E$5:E$278) -> 13 | E9: =SUMPRODUCT((LEFT('IG Giornaliero'!$A$5:$A$278,7)=$A9)*'IG Giornaliero'!F$5:F$278) -> 11 | F9: =SUMPRODUCT((LEFT('IG Giornaliero'!$A$5:$A$278,7)=$A9)*'IG Giornaliero'!H$5:H$278) -> 0 | G9: =SUMPRODUCT((LEFT('IG Giornaliero'!$A$5:$A$278,7)=$A9)*'IG Giornaliero'!I$5:I$278) -> 1
A10: 2026-06 | B10: =SUMPRODUCT((LEFT('IG Giornaliero'!$A$5:$A$278,7)=$A10)*'IG Giornaliero'!B$5:B$278) -> 218 | C10: =SUMPRODUCT((LEFT('IG Giornaliero'!$A$5:$A$278,7)=$A10)*'IG Giornaliero'!C$5:C$278) -> 398 | D10: =SUMPRODUCT((LEFT('IG Giornaliero'!$A$5:$A$278,7)=$A10)*'IG Giornaliero'!E$5:E$278) -> 26 | E10: =SUMPRODUCT((LEFT('IG Giornaliero'!$A$5:$A$278,7)=$A10)*'IG Giornaliero'!F$5:F$278) -> 24 | F10: =SUMPRODUCT((LEFT('IG Giornaliero'!$A$5:$A$278,7)=$A10)*'IG Giornaliero'!H$5:H$278) -> 0 | G10: =SUMPRODUCT((LEFT('IG Giornaliero'!$A$5:$A$278,7)=$A10)*'IG Giornaliero'!I$5:I$278) -> 1
A11: 2026-07 | B11: =SUMPRODUCT((LEFT('IG Giornaliero'!$A$5:$A$278,7)=$A11)*'IG Giornaliero'!B$5:B$278) -> 316 | C11: =SUMPRODUCT((LEFT('IG Giornaliero'!$A$5:$A$278,7)=$A11)*'IG Giornaliero'!C$5:C$278) -> 737 | D11: =SUMPRODUCT((LEFT('IG Giornaliero'!$A$5:$A$278,7)=$A11)*'IG Giornaliero'!E$5:E$278) -> 42 | E11: =SUMPRODUCT((LEFT('IG Giornaliero'!$A$5:$A$278,7)=$A11)*'IG Giornaliero'!F$5:F$278) -> 30 | F11: =SUMPRODUCT((LEFT('IG Giornaliero'!$A$5:$A$278,7)=$A11)*'IG Giornaliero'!H$5:H$278) -> 0 | G11: =SUMPRODUCT((LEFT('IG Giornaliero'!$A$5:$A$278,7)=$A11)*'IG Giornaliero'!I$5:I$278) -> 6
A12: 2026-08 | B12: =SUMPRODUCT((LEFT('IG Giornaliero'!$A$5:$A$278,7)=$A12)*'IG Giornaliero'!B$5:B$278) -> 117 | C12: =SUMPRODUCT((LEFT('IG Giornaliero'!$A$5:$A$278,7)=$A12)*'IG Giornaliero'!C$5:C$278) -> 219 | D12: =SUMPRODUCT((LEFT('IG Giornaliero'!$A$5:$A$278,7)=$A12)*'IG Giornaliero'!E$5:E$278) -> 8 | E12: =SUMPRODUCT((LEFT('IG Giornaliero'!$A$5:$A$278,7)=$A12)*'IG Giornaliero'!F$5:F$278) -> 8 | F12: =SUMPRODUCT((LEFT('IG Giornaliero'!$A$5:$A$278,7)=$A12)*'IG Giornaliero'!H$5:H$278) -> 0 | G12: =SUMPRODUCT((LEFT('IG Giornaliero'!$A$5:$A$278,7)=$A12)*'IG Giornaliero'!I$5:I$278) -> 0
A13: 2026-09 | B13: =SUMPRODUCT((LEFT('IG Giornaliero'!$A$5:$A$278,7)=$A13)*'IG Giornaliero'!B$5:B$278) -> 4549 | C13: =SUMPRODUCT((LEFT('IG Giornaliero'!$A$5:$A$278,7)=$A13)*'IG Giornaliero'!C$5:C$278) -> 5797 | D13: =SUMPRODUCT((LEFT('IG Giornaliero'!$A$5:$A$278,7)=$A13)*'IG Giornaliero'!E$5:E$278) -> 30 | E13: =SUMPRODUCT((LEFT('IG Giornaliero'!$A$5:$A$278,7)=$A13)*'IG Giornaliero'!F$5:F$278) -> 22 | F13: =SUMPRODUCT((LEFT('IG Giornaliero'!$A$5:$A$278,7)=$A13)*'IG Giornaliero'!H$5:H$278) -> 5 | G13: =SUMPRODUCT((LEFT('IG Giornaliero'!$A$5:$A$278,7)=$A13)*'IG Giornaliero'!I$5:I$278) -> 1
A14: 2026-10 | B14: =SUMPRODUCT((LEFT('IG Giornaliero'!$A$5:$A$278,7)=$A14)*'IG Giornaliero'!B$5:B$278) -> 14 | C14: =SUMPRODUCT((LEFT('IG Giornaliero'!$A$5:$A$278,7)=$A14)*'IG Giornaliero'!C$5:C$278) -> 38 | D14: =SUMPRODUCT((LEFT('IG Giornaliero'!$A$5:$A$278,7)=$A14)*'IG Giornaliero'!E$5:E$278) -> 0 | E14: =SUMPRODUCT((LEFT('IG Giornaliero'!$A$5:$A$278,7)=$A14)*'IG Giornaliero'!F$5:F$278) -> 0 | F14: =SUMPRODUCT((LEFT('IG Giornaliero'!$A$5:$A$278,7)=$A14)*'IG Giornaliero'!H$5:H$278) -> 0 | G14: =SUMPRODUCT((LEFT('IG Giornaliero'!$A$5:$A$278,7)=$A14)*'IG Giornaliero'!I$5:I$278) -> 0
A15: Totale | B15: =SUM(B5:B14) -> 5802 | C15: =SUM(C5:C14) -> 8323 | D15: =SUM(D5:D14) -> 168 | E15: =SUM(E5:E14) -> 135 | F15: =SUM(F5:F14) -> 5 | G15: =SUM(G5:G14) -> 13

Sheet IG Contenuti
A1: Profilo Instagram · contenuti del periodo
A4: Data | B4: Formato | C4: Testo | D4: Copertura | E4: Visualizzazioni | F4: Mi piace | G4: Commenti | H4: Salvataggi | I4: Condivisioni | J4: Interazioni | K4: Link
A5: 2026-02-19 | B5: Carosello | C5: Gen&Sys è un’azienda a conduzione familiare che da oltre 15 anni lavora a fianco degli installatori. Non siamo un semplice punto di fornitura, ma un partner tecnico che affianca ogni progetto, dalla scelta dell’impianto alla gestione delle pratiche. 049 9802495 | info@genesyssrl.com #genesys #genesyssrl #termoidraulica #riscaldamento #climatizzazione | D5: 26 | E5: 50 | F5: 4 | G5: 0 | H5: 0 | I5: 0 | J5: 4 | K5: https://www.instagram.com/p/DU71TRzjd4U/
A6: 2026-02-23 | B6: Foto | C6: 📍La nostra sede - Vigonovo (VE) Un punto di riferimento per gli installatori del territorio. Qui lavoriamo ogni giorno per affiancare chi opera nel settore impiantistico, con supporto tecnico, consulenza e gestione delle pratiche. 049 9802495 | info@genesyssrl.com #genesys #genesyssrl #termoidraulica #riscaldamento #climatizzazione #pompedicalore #daikin #lgelectronics #chaffoteaux #bwt #aristonthermogroup | D6: 76 | E6: 141 | F6: 4 | G6: 0 | H6: 0 | I6: 1 | J6: 5 | K6: https://www.instagram.com/p/DVGRQ5PCMdJ/
A7: 2026-02-25 | B7: Carosello | C7: Ogni impianto ha esigenze diverse. Per questo noi di Gen&Sys proponiamo una gamma completa di soluzioni impiantistiche, selezionate per adattarsi a contesti, configurazioni e necessità differenti. Non un unico prodotto, ma più possibilità tra cui scegliere, con il supporto tecnico giusto per individuare quella corretta. 049 9802495 | info@genesyssrl.com #genesys #genesyssrl #termoidraulica #riscaldamento #climatizzazione #pompedicalore #daikin #lgelectronics #chaffoteaux #bwt #aristonthermogroup | D7: 64 | E7: 111 | F7: 5 | G7: 0 | H7: 0 | I7: 1 | J7: 6 | K7: https://www.instagram.com/p/DVLa4s5jdhI/
A8: 2026-02-27 | B8: Carosello | C8: La differenza non è solo in cosa fornisci, ma nel supporto che dai. Gen&Sys affianca gli installatori con un servizio completo, pensato per semplificare il lavoro e ridurre le complessità operative. Dalla consulenza tecnica alla gestione delle pratiche, siamo presenti in ogni fase. 049 9802495 | info@genesyssrl.com #genesys #genesyssrl #termoidraulica #riscaldamento #climatizzazione #pompedicalore #daikin #lgelectronics #chaffoteaux #bwt #aristonthermogroup | D8: 24 | E8: 70 | F8: 4 | G8: 0 | H8: 0 | I8: 0 | J8: 4 | K8: https://www.instagram.com/p/DVQkcx9jFAH/
A9: 2026-03-02 | B9: Carosello | C9: ll 𝐂𝐎𝐍𝐓𝐎 𝐓𝐄𝐑𝐌𝐈𝐂𝐎 𝟑.𝟎 è la nuova misura di incentivo statale che sostiene interventi per l’efficienza energetica e la produzione di calore da fonti rinnovabili, come l’installazione di pompe di calore ad alta efficienza. Il contributo è a fondo perduto e può coprire fino al 65% delle spese ammissibili per privati e imprese, con casi particolari fino al 100% per edifici pubblici. La misura è uno strumento concreto per ridurre l’investimento iniziale e accelerare la transizione verso soluzioni più efficienti. Noi di Gen&Sys ci occupiamo della gestione completa della pratica, fornendo tutta la documentazione e le certificazioni necessarie. 049 9802495 | info@genesyssrl.com #genesys #genesyssrl #termoidraulica #riscaldamento #climatizzazione #pompedicalore #daikin #lgelectronics #chaffoteaux #bwt #aristonthermogroup | D9: 61 | E9: 115 | F9: 4 | G9: 0 | H9: 0 | I9: 1 | J9: 5 | K9: https://www.instagram.com/p/DVYS5ZICHwZ/
A10: 2026-03-05 | B10: Foto | C10: Ogni impianto ha esigenze diverse. Per questo Gen&Sys propone soluzioni di 6 brand selezionati, così da offrire alternative concrete in base a contesto, configurazione e obiettivi del cliente finale. Avere più possibilità significa poter scegliere la soluzione più adatta, non la più standard. Il prodotto giusto nasce da una valutazione attenta. A supporto delle scelte impiantistiche, sempre. 049 9802495 | info@genesyssrl.com #genesys #genesyssrl #termoidraulica #riscaldamento #climatizzazione #pompedicalore #daikin #lgelectronics #chaffoteaux #bwt #aristonthermogroup | D10: 23 | E10: 49 | F10: 5 | G10: 0 | H10: 0 | I10: 0 | J10: 5 | K10: https://www.instagram.com/p/DVgBOGaD5Xi/
A11: 2026-04-07 | B11: Foto | C11: 📍Dove si trova la nostra sede? In Via Sagredo 21, a Vigonovo. Facilmente raggiungibile dalle principali direttrici tra Padova, Venezia e la Riviera del Brenta 049 9802495 | info@genesyssrl.com #genesys #genesyssrl #termoidraulica #riscaldamento #climatizzazione #pompedicalore #daikin #lgelectronics #chaffoteaux #bwt #aristonthermogroup | D11: 34 | E11: 83 | F11: 4 | G11: 0 | H11: 0 | I11: 0 | J11: 4 | K11: https://www.instagram.com/p/DW1b_sHFgJt/
A12: 2026-04-15 | B12: Carosello | C12: La pompa di calore non è sempre la soluzione giusta. Dipende dall’edificio, dall’impianto esistente e dagli obiettivi energetici. Capire quando conviene installarla – e quando è meglio valutare un sistema diverso – è il primo passo per un impianto che funzioni davvero nel tempo. La scelta parte dall’analisi, non dalla tendenza. 049 9802495 | info@genesyssrl.com #genesys #genesyssrl #termoidraulica #riscaldamento #climatizzazione #pompedicalore #daikin #lgelectronics #chaffoteaux #bwt #aristonthermogroup | D12: 22 | E12: 47 | F12: 5 | G12: 0 | H12: 0 | I12: 0 | J12: 5 | K12: https://www.instagram.com/p/DXJfCM4jUBE/
A13: 2026-04-22 | B13: Reel | C13: Gen&Sys si racconta anche attraverso i numeri. Esperienza, progetti realizzati, collaborazioni costruite nel tempo e competenze tecniche dedicate: sono questi gli elementi che definiscono il nostro percorso. 049 9802495 | info@genesyssrl.com #genesys #genesyssrl #termoidraulica #riscaldamento #climatizzazione #pompedicalore #daikin #lgelectronics #chaffoteaux #bwt #aristonthermogroup | D13: 32 | E13: 51 | F13: 4 | G13: 0 | H13: 0 | I13: 1 | J13: 5 | K13: https://www.instagram.com/reel/DXbgv1lDuiA/
A14: 2026-05-13 | B14: Carosello | C14: Scegliere una pompa di calore non significa solo guardare i kW dichiarati. Il dimensionamento corretto parte da carico termico reale, regime di funzionamento, terminali esistenti e obiettivi energetici dell’edificio. Un impianto sovradimensionato lavora male. Uno sottodimensionato non garantisce comfort. La differenza sta nella valutazione tecnica iniziale. 049 9802495 | info@genesyssrl.com | D14: 22 | E14: 51 | F14: 4 | G14: 0 | H14: 0 | I14: 0 | J14: 4 | K14: https://www.instagram.com/p/DYRlO2fD1ex/
A15: 2026-05-27 | B15: Reel | C15: Conto Termico 3.0 un’opportunità concreta per rendere più efficiente la tua casa o la tua azienda. Il nuovo incentivo sostiene interventi per migliorare l’efficienza energetica e favorire l’utilizzo di fonti rinnovabili, con contributi fino al 65% delle spese ammissibili. Caldaie, pompe di calore, solare termico e altri interventi possono diventare oggi un investimento più accessibile, con benefici immediati su consumi, comfort e sostenibilità. Approfitta del Conto Termico 3.0 e trasforma l’efficienza in valore. 📩 Contattaci per scoprire quali interventi possono rientrare nell’incentivo. 049 9802495 | info@genesyssrl.com | D15: 248 | E15: 302 | F15: 7 | G15: 0 | H15: 0 | I15: 3 | J15: 10 | K15: https://www.instagram.com/reel/DY1okNyDQCz/
A16: 2026-06-11 | B16: Carosello | C16: Ogni progetto ha esigenze diverse. Per questo Gen&Sys non propone pacchetti standard, ma soluzioni impiantistiche pensate in base al contesto, agli obiettivi e alle necessità del cliente. Dalle caldaie a gas ai sistemi ibridi, dalle pompe di calore alla climatizzazione VRV/VRF, seguiamo impianti in ambito domestico, civile e industriale con un approccio flessibile e concreto. Perché un impianto efficiente nasce prima di tutto da una progettazione adatta alla realtà in cui verrà installato. 📩 Raccontaci le tue esigenze: ti aiutiamo a trovare la soluzione più adatta. 049 9802495 | info@genesyssrl.com | D16: 31 | E16: 107 | F16: 3 | G16: 0 | H16: 0 | I16: 0 | J16: 3 | K16: https://www.instagram.com/p/DZcQqYFlimp/
... A31: 2026-09-30 | B31: Carosello | C31: Due preventivi per lo stesso edificio possono arrivare a dimensionamenti diversi. Il punto non è capire semplicemente chi propone più o meno kW, ma da quali dati nasce quel numero. Un dimensionamento serio deve poter essere spiegato: dispersioni, condizioni di progetto, terminali e temperature di lavoro. Perché una scelta tecnica è davvero utile quando se ne comprende il perché. 049 9802495 | info@genesyssrl.com | D31: 26 | E31: 81 | F31: 3 | G31: 0 | H31: 0 | I31: 0 | J31: 4 | K31: https://www.instagram.com/p/Dd6Eek8lCBN/
A34: Media per formato
A35: Formato | B35: Contenuti | C35: Copertura media | D35: Visualizzazioni medie | E35: Interazioni medie
A36: Reel | B36: =COUNTIF($B$5:$B$31,A36) -> 5 | C36: =IFERROR(AVERAGEIF($B$5:$B$31,A36,$D$5:$D$31),0) -> 165.6 | D36: =IFERROR(AVERAGEIF($B$5:$B$31,A36,$E$5:$E$31),0) -> 220.2 | E36: =IFERROR(AVERAGEIF($B$5:$B$31,A36,$J$5:$J$31),0) -> 10.2
A37: Foto | B37: =COUNTIF($B$5:$B$31,A37) -> 3 | C37: =IFERROR(AVERAGEIF($B$5:$B$31,A37,$D$5:$D$31),0) -> 44.333333 | D37: =IFERROR(AVERAGEIF($B$5:$B$31,A37,$E$5:$E$31),0) -> 91 | E37: =IFERROR(AVERAGEIF($B$5:$B$31,A37,$J$5:$J$31),0) -> 4.6666667
A38: Carosello | B38: =COUNTIF($B$5:$B$31,A38) -> 19 | C38: =IFERROR(AVERAGEIF($B$5:$B$31,A38,$D$5:$D$31),0) -> 30.736842 | D38: =IFERROR(AVERAGEIF($B$5:$B$31,A38,$E$5:$E$31),0) -> 74.421053 | E38: =IFERROR(AVERAGEIF($B$5:$B$31,A38,$J$5:$J$31),0) -> 3.7368421
